simple_ulid-1.0.0.dist-info/licenses/LICENSE
ulid/__init__.py
ulid/main.py
simple_ulid-1.0.0.dist-info/METADATA
simple_ulid-1.0.0.dist-info/WHEEL
simple_ulid-1.0.0.dist-info/top_level.txt
simple_ulid-1.0.0.dist-info/RECORD
